Workbook

Sheet Inputs
A1: Assumption | B1: Value | C1: Notes
A2: Addressable Nigerian lawyer market | B2: 220000 | C2: Planning midpoint of commonly discussed 200,000 to 250,000 range
A3: Yearly premium price | B3: 100000 | C3: Current LearnedCircle yearly premium price
A4: Monthly premium price | B4: 10000 | C4: Current monthly premium price
A5: Job and advert revenue base | B5: 25000000 | C5: Conservative annual marketplace revenue starting point
A6: Annual revenue growth | B6: 0.45 | C6: Illustrative growth as adoption improves
A7: Gross margin | B7: 0.72 | C7: Digital subscription and marketplace gross margin assumption
A8: Marketing as % revenue | B8: 0.28 | C8: Front-loaded customer acquisition
A9: Payroll as % revenue | B9: 0.3 | C9: Hiring for product, operations, verification and content
A10: Admin/technology as % revenue | B10: 0.16 | C10: Hosting, tools, admin, compliance and support

Sheet 5-Year Model
A1: Metric | B1: Year 1 | C1: Year 2 | D1: Year 3 | E1: Year 4 | F1: Year 5
A2: Lawyers onboarded | B2: 5000 | C2: 11000 | D2: 22000 | E2: 36000 | F2: 52000
A3: Premium conversion | B3: 0.08 | C3: 0.12 | D3: 0.2 | E3: 0.25 | F3: 0.3
A4: Premium lawyers | B4: =B2*B3 | C4: =C2*C3 | D4: =D2*D3 | E4: =E2*E3 | F4: =F2*F3
A5: Premium revenue | B5: =B4*Inputs!$B$3 | C5: =C4*Inputs!$B$3 | D5: =D4*Inputs!$B$3 | E5: =E4*Inputs!$B$3 | F5: =F4*Inputs!$B$3
A6: Jobs and adverts | B6: =Inputs!$B$5 | C6: =B6*(1+Inputs!$B$6) | D6: =C6*(1+Inputs!$B$6) | E6: =D6*(1+Inputs!$B$6) | F6: =E6*(1+Inputs!$B$6)
A7: Total revenue | B7: =B5+B6 | C7: =C5+C6 | D7: =D5+D6 | E7: =E5+E6 | F7: =F5+F6
A8: Gross profit | B8: =B7*Inputs!$B$7 | C8: =C7*Inputs!$B$7 | D8: =D7*Inputs!$B$7 | E8: =E7*Inputs!$B$7 | F8: =F7*Inputs!$B$7
A9: Marketing | B9: =B7*Inputs!$B$8 | C9: =C7*Inputs!$B$8 | D9: =D7*Inputs!$B$8 | E9: =E7*Inputs!$B$8 | F9: =F7*Inputs!$B$8
A10: Payroll | B10: =B7*Inputs!$B$9 | C10: =C7*Inputs!$B$9 | D10: =D7*Inputs!$B$9 | E10: =E7*Inputs!$B$9 | F10: =F7*Inputs!$B$9
A11: Admin and technology | B11: =B7*Inputs!$B$10 | C11: =C7*Inputs!$B$10 | D11: =D7*Inputs!$B$10 | E11: =E7*Inputs!$B$10 | F11: =F7*Inputs!$B$10
A12: Operating profit | B12: =B8-B9-B10-B11 | C12: =C8-C9-C10-C11 | D12: =D8-D9-D10-D11 | E12: =E8-E9-E10-E11 | F12: =F8-F9-F10-F11
A13: Closing cash before financing | B13: =B12 | C13: =B13+C12 | D13: =C13+D12 | E13: =D13+E12 | F13: =E13+F12

Sheet Scenarios
A1: Scenario | B1: Lawyers onboarded | C1: Premium conversion | D1: Premium lawyers | E1: Premium ARR | F1: Jobs + adverts | G1: Total annual potential
A2: Conservative | B2: 11000 | C2: 0.1 | D2: =B2*C2 | E2: =D2*Inputs!$B$3 | F2: 25000000 | G2: =E2+F2
A3: Base case | B3: 22000 | C3: 0.2 | D3: =B3*C3 | E3: =D3*Inputs!$B$3 | F3: 80000000 | G3: =E3+F3
A4: Upside | B4: 44000 | C4: 0.3 | D4: =B4*C4 | E4: =D4*Inputs!$B$3 | F4: 200000000 | G4: =E4+F4

Sheet Use of Funds
A1: Use of funds | B1: N100m round | C1: N200m round | D1: N500m round | E1: Rationale
A2: Marketing and lawyer acquisition | B2: =100000000*B2 | C2: =200000000*C2 | D2: =500000000*D2 | E2: NBA branch visibility, digital campaigns, content and employer partnerships
A3: Hiring and operations | B3: =100000000*B3 | C3: =200000000*C3 | D3: =500000000*D3 | E3: Product, support, verification, content and partnerships
A4: Technology and security | B4: =100000000*B4 | C4: =200000000*C4 | D4: =500000000*D4 | E4: Payments, mobile app, AI assistant, analytics and document workflows
A5: Legal, compliance and admin | B5: =100000000*B5 | C5: =200000000*C5 | D5: =500000000*D5 | E5: Governance, accounting, contracts and policies
A6: Reserve | B6: =100000000*B6 | C6: =200000000*C6 | D6: =500000000*D6 | E6: Working capital and execution buffer

Sheet Dashboard
A1: LearnedCircle Financial Model
A3: Investment ladder | D3: Base case annual potential
A4: N100m for 12% | D4: =Scenarios!G3
A5: N200m for 15%
A6: N500m for 20%
